jwst-1.20.2.dist-info/RECORD
jwst-1.20.2.dist-info/WHEEL
jwst-1.20.2.dist-info/entry_points.txt
jwst-1.20.2.dist-info/top_level.txt
jwst-1.20.2.dist-info/METADATA
jwst-1.20.2.dist-info/licenses/LICENSE
jwst/conftest.py
jwst/_version.py
jwst/__init__.py
jwst/step.py
jwst/background/background_sub_wfss.py
jwst/background/background_sub.py
jwst/background/asn_intake.py
jwst/background/subtract_images.py
jwst/background/__init__.py
jwst/background/background_sub_soss.py
jwst/background/background_step.py
jwst/background/tests/test_background_soss.py
jwst/background/tests/__init__.py
jwst/background/tests/test_background.py
jwst/background/tests/test_background_wfss.py
jwst/background/tests/data/test_cat.ecsv
jwst/ami/ami_average.py
jwst/ami/nrm_core.py
jwst/ami/ami_normalize_step.py
jwst/ami/ami_analyze.py
jwst/ami/leastsqnrm.py
jwst/ami/matrix_dft.py
jwst/ami/hextransformee.py
jwst/ami/__init__.py
jwst/ami/utils.py
jwst/ami/instrument_data.py
jwst/ami/find_affine2d_parameters.py
jwst/ami/mask_definition_ami.py
jwst/ami/analyticnrm2.py
jwst/ami/ami_normalize.py
jwst/ami/ami_average_step.py
jwst/ami/ami_analyze_step.py
jwst/ami/oifits.py
jwst/ami/lg_model.py
jwst/ami/bp_fix.py
jwst/ami/tests/test_instrument_data.py
jwst/ami/tests/test_utils.py
jwst/ami/tests/conftest.py
jwst/ami/tests/test_analyticnrm2.py
jwst/ami/tests/test_find_affine2d_parameters.py
jwst/ami/tests/test_ami_average.py
jwst/ami/tests/__init__.py
jwst/ami/tests/test_bp_fix.py
jwst/ami/tests/test_nrm_core.py
jwst/ami/tests/test_ami_analyze.py
jwst/ami/tests/test_lg_model.py
jwst/ami/tests/test_hextransformee.py
jwst/ami/tests/test_matrix_dft.py
jwst/ami/tests/helpers.py
jwst/ami/tests/test_leastsqnrm.py
jwst/ami/tests/test_mask_definition_ami.py
jwst/ami/tests/test_ami_normalize.py
jwst/pixel_replace/pixel_replace_step.py
jwst/pixel_replace/__init__.py
jwst/pixel_replace/pixel_replace.py
jwst/pixel_replace/tests/__init__.py
jwst/pixel_replace/tests/test_pixel_replace.py
jwst/pathloss/__init__.py
jwst/pathloss/pathloss.py
jwst/pathloss/pathloss_step.py
jwst/pathloss/tests/__init__.py
jwst/pathloss/tests/test_pathloss.py
