Metadata-Version: 2.4
Name: jwst
Version: 1.20.2
Summary: Library for calibration of science observations from the James Webb Space Telescope
Author: JWST calibration pipeline developers
Project-URL: Homepage, https://github.com/spacetelescope/jwst
Project-URL: Tracker, https://github.com/spacetelescope/jwst/issues
Project-URL: Documentation, https://jwst-pipeline.readthedocs.io/en/stable/
Project-URL: Source Code, https://github.com/spacetelescope/jwst
Classifier: Intended Audience :: Science/Research
Classifier: Topic :: Scientific/Engineering :: Astronomy
Classifier: Operating System :: MacOS :: MacOS X
Classifier: Operating System :: POSIX
Classifier: Programming Language :: Python :: 3
Classifier: Programming Language :: Python :: 3 :: Only
Classifier: Programming Language :: Python :: 3.11
Classifier: Programming Language :: Python :: 3.12
Classifier: Programming Language :: Python :: 3.13
Requires-Python: <3.14,>=3.11
License-File: LICENSE
Requires-Dist: asdf<6,>=4.2
Requires-Dist: astropy>=6.1
Requires-Dist: BayesicFitting>=3.2.2
Requires-Dist: crds>=12.0.3
Requires-Dist: drizzle<2.2.0,>=2.1.1
Requires-Dist: gwcs<0.27.0,>=0.26.0
Requires-Dist: numpy>=1.25
Requires-Dist: photutils>=2.1.0
Requires-Dist: pyparsing>=2.2.1
Requires-Dist: requests>=2.31
Requires-Dist: scikit-image>=0.20.0
Requires-Dist: scipy>=1.14.1
Requires-Dist: spherical-geometry>=1.3
Requires-Dist: stdatamodels<4.2.0,>=4.1.0
Requires-Dist: stcal<1.16.0,>=1.15.2
Requires-Dist: stpipe<0.12.0,>=0.11.1
Requires-Dist: stsci.imagestats>=1.6.3
Requires-Dist: synphot>=1.3
Requires-Dist: tweakwcs>=0.8.8
Requires-Dist: wiimatch>=0.3.2
Requires-Dist: packaging>20.0
Requires-Dist: importlib-metadata>=4.11.4
Requires-Dist: jsonschema>=4.8
Provides-Extra: docs
Requires-Dist: matplotlib; extra == "docs"
Requires-Dist: numpydoc; extra == "docs"
Requires-Dist: sphinx; extra == "docs"
Requires-Dist: sphinxcontrib-jquery; extra == "docs"
Requires-Dist: sphinx-automodapi; extra == "docs"
Requires-Dist: sphinx-rtd-theme; extra == "docs"
Requires-Dist: pytest-doctestplus>=0.11; extra == "docs"
Provides-Extra: sdp
Requires-Dist: jplephem>=2.9; extra == "sdp"
Requires-Dist: pysiaf>=0.13.0; extra == "sdp"
Provides-Extra: test
Requires-Dist: ci-watson>=0.10; extra == "test"
Requires-Dist: pysiaf>=0.13.0; extra == "test"
Requires-Dist: pytest>=6.0.0; extra == "test"
Requires-Dist: pytest-cov>=2.9.0; extra == "test"
Requires-Dist: pytest-doctestplus>=0.10.0; extra == "test"
Requires-Dist: requests_mock>=1.0; extra == "test"
Provides-Extra: contrib
Requires-Dist: pre-commit>=4.1.0; extra == "contrib"
Requires-Dist: jwst[docs,test]; extra == "contrib"
Dynamic: license-file
